{
    "pools": [
        {
            "rolls": {
                "min": 0,
                "max": 2
            },
            "bonus_rolls": {
                "min": 0,
                "max": 2
            },
            "entries": [
                {
                    "type": "loot_table",
                    "value": "hunger/sword",
                    "weight": 4,
                    "quality": 2
                },
                {
                    "type": "loot_table",
                    "value": "hunger/skills",
                    "weight": 1,
                    "quality": 3
                }
            ]
        },
        {
            "rolls": {
                "min": 0,
                "max": 1
            },
            "bonus_rolls": {
                "min": 2,
                "max": 4
            },
            "entries": [
                {
                    "type": "loot_table",
                    "value": "hunger/potion",
                    "weight": 5,
                    "quality": 2
                },
                {
                    "type": "loot_table",
                    "value": "hunger/other",
                    "weight": 1,
                    "quality": 3
                },
                {
                    "type": "loot_table",
                    "value": "hunger/sword",
                    "weight": 4,
                    "quality": 2
                }
            ]
        },
        {
            "rolls": {
                "min": 0,
                "max": 2
            },
            "bonus_rolls": {
                "min": 2,
                "max": 4
            },
            "entries": [
                {
                    "type": "loot_table",
                    "value": "hunger/armor",
                    "weight": 5,
                    "quality": 2
                }
            ]
        },
        {
            "rolls": {
                "min": 0,
                "max": 1
            },
            "bonus_rolls": {
                "min": 2,
                "max": 4
            },
            "entries": [
                {
                    "type": "loot_table",
                    "value": "hunger/potion",
                    "weight": 3,
                    "quality": 2
                },
                {
                    "type": "loot_table",
                    "value": "hunger/other",
                    "weight": 3,
                    "quality": 3
                }
            ]
        }
    ]
}
