{
    "display": {
        "title": [
            "维护中的游戏"
        ],
        "description": [
            "\u00a7b你说什么？这个游戏在维护？！\n\u00a77\u00a7n\u00a7m你说有没有可能是BUG太多了被禁了。"
        ],
        "icon": {
            "id": "minecraft:iron_golem_spawn_egg"
        },
        "frame": "task",
        "show_toast": true,
        "announce_to_chat": true,
        "hidden": true
    },
    "parent": "minecraft:unbelievable",
    "criteria": {
        "a": {
            "trigger": "minecraft:impossible"
        }
    },
    "requirements": [
        [
            "a"
        ]
    ],
    "rewards": {}
}
